README.rst
setup.py
thealot/__init__.py
thealot/config.json
thealot/thealot.py
thealot.egg-info/PKG-INFO
thealot.egg-info/SOURCES.txt
thealot.egg-info/dependency_links.txt
thealot.egg-info/requires.txt
thealot.egg-info/top_level.txt
thealot/plugins/__init__.py
thealot/plugins/plugin.py