Metadata-Version: 1.0
Name: thealot
Version: 0.2.1
Summary: A lightweight IRC bot framework.
Home-page: https://github.com/nCrazed/TheAlot
Author: Edvin "nCrazed" Malinovskis
Author-email: edvin.malinovskis@gmail.com
License: UNKNOWN
Platform: UNKNOWN
